superdata/__init__.py
superdata-0.1.1.dist-info/LICENSE
superdata-0.1.1.dist-info/METADATA
superdata-0.1.1.dist-info/WHEEL
superdata-0.1.1.dist-info/top_level.txt
superdata-0.1.1.dist-info/RECORD
