Metadata-Version: 2.1
Name: superdata
Version: 0.1.1
Summary: A super package that imports datascience packages to the namespace
Home-page: https://github.com/atmostafa/superdata
Author: Mostafa
Author-email: EmailAtMostafa@gmail.com
License: UNKNOWN
Platform: UNKNOWN
Classifier: Programming Language :: Python :: 3
Classifier: License :: OSI Approved :: MIT License
Classifier: Operating System :: OS Independent
Requires-Python: >=3
Requires-Dist: numpy
Requires-Dist: matplotlib
Requires-Dist: pandas
